MANIFEST.in
README.md
setup.cfg
setup.py
analytics/__init__.py
analytics/client.py
analytics/consumer.py
analytics/request.py
analytics/s3_consumer.py
analytics/utils.py
analytics/version.py
analytics/test/__init__.py
analytics/test/client.py
analytics/test/consumer.py
analytics/test/module.py
analytics/test/request.py
analytics/test/utils.py
analytics_python_findhotel.egg-info/PKG-INFO
analytics_python_findhotel.egg-info/SOURCES.txt
analytics_python_findhotel.egg-info/dependency_links.txt
analytics_python_findhotel.egg-info/requires.txt
analytics_python_findhotel.egg-info/top_level.txt