Metadata-Version: 1.1
Name: analytics-python-findhotel
Version: 1.5.0
Summary: FindHotel's fork of Segment's Python SDK.
Home-page: https://github.com/findhotel/analytics-python
Author: FindHotel BV
Author-email: german@findhotel.net
License: MIT License
Platform: UNKNOWN
Classifier: Development Status :: 5 - Production/Stable
Classifier: Intended Audience :: Developers
Classifier: License :: OSI Approved :: MIT License
Classifier: Operating System :: OS Independent
Classifier: Programming Language :: Python
Classifier: Programming Language :: Python :: 3
Classifier: Programming Language :: Python :: 3.5
Classifier: Programming Language :: Python :: 3.6
Classifier: Programming Language :: Python :: 3.7
